maileroo/__init__.py
maileroo/attachment.py
maileroo/client.py
maileroo/email_address.py
maileroo-1.0.0.dist-info/licenses/LICENSE
maileroo-1.0.0.dist-info/METADATA
maileroo-1.0.0.dist-info/WHEEL
maileroo-1.0.0.dist-info/top_level.txt
maileroo-1.0.0.dist-info/RECORD
