Metadata-Version: 2.4
Name: maileroo
Version: 1.0.0
Summary: This package contains the Python SDK to help you integrate with Maileroo's email sending API efficiently and effectively.
Author-email: Maileroo <support@maileroo.com>
License: MIT
Project-URL: Homepage, https://maileroo.com
Project-URL: Source, https://github.com/maileroo/maileroo-python-sdk
Requires-Python: >=3.8
License-File: LICENSE
Requires-Dist: requests>=2.28.0
Requires-Dist: python-magic>=0.4.27; platform_system != "Windows"
Dynamic: license-file
